sphinx_ext_vizjs/__init__.py
sphinx_ext_vizjs/viz-standalone.js
sphinx_ext_vizjs-0.1.1.dist-info/METADATA
sphinx_ext_vizjs-0.1.1.dist-info/WHEEL
sphinx_ext_vizjs-0.1.1.dist-info/top_level.txt
sphinx_ext_vizjs-0.1.1.dist-info/RECORD
