Metadata-Version: 2.4
Name: sphinx-ext-vizjs
Version: 0.1.1
Summary: Sphinx extention for vizjs
Requires-Python: >=3.11
Requires-Dist: sphinx>=8
